anki_connect_api.py
anki_connect_api-24.2.26.0.dist-info/LICENSE
anki_connect_api-24.2.26.0.dist-info/METADATA
anki_connect_api-24.2.26.0.dist-info/WHEEL
anki_connect_api-24.2.26.0.dist-info/top_level.txt
anki_connect_api-24.2.26.0.dist-info/RECORD
