Metadata-Version: 2.1
Name: anki_connect_api
Version: 24.2.26.0
Summary: Use the Anki-Connect plugin from Python code
Author: bitmonster
License: Copyright (c) 2018 The Python Packaging Authority
Project-URL: Homepage, https://github.com/bbitmonster/anki-connect-api
Classifier: Programming Language :: Python :: 3
Classifier: License :: OSI Approved :: MIT License
Classifier: Operating System :: OS Independent
Requires-Python: >=3.8
License-File: LICENSE
